LICENSE
README.rst
setup.py
pySRU/ElectricalField.py
pySRU/ElectronBeam.py
pySRU/MagneticField.py
pySRU/MagneticStructure.py
pySRU/MagneticStructureBendingMagnet.py
pySRU/MagneticStructureUndulatorPlane.py
pySRU/Radiation.py
pySRU/RadiationFactory.py
pySRU/Simulation.py
pySRU/Source.py
pySRU/SourceBendingmagnet.py
pySRU/SourceUndulatorPlane.py
pySRU/Trajectory.py
pySRU/TrajectoryFactory.py
pySRU/__init__.py
pySRU/main.py
pySRU.egg-info/PKG-INFO
pySRU.egg-info/SOURCES.txt
pySRU.egg-info/dependency_links.txt
pySRU.egg-info/requires.txt
pySRU.egg-info/top_level.txt
pySRU/tests/AllTests.py
pySRU/tests/MagneticFieldTest.py
pySRU/tests/MagneticStructureTest.py
pySRU/tests/MainTest.py
pySRU/tests/RadiationFactorytest.py
pySRU/tests/RadiationTest.py
pySRU/tests/SimulationTest.py
pySRU/tests/SourceTest.py
pySRU/tests/TrajectoryFactoryTest.py
pySRU/tests/TrajectoryTest.py
pySRU/tests/__init__.py