Metadata-Version: 2.1
Name: pySRU
Version: 0.5.5
Summary: Python synchrotron undulator calcution
Home-page: https://github.com/SophieTh/und_Sophie_2016/
Author: Sophie Thery, Mark Glass, Manuel Sanchez del Rio
Author-email: srio@esrf.eu
License: UNKNOWN
Platform: UNKNOWN
License-File: LICENSE
